LICENSE
MANIFEST.in
setup.py
DRConverter/__init__.py
DRConverter/dr_converter.py
DRConverter/Lib/__init__.py
DRConverter/Lib/converters/__init__.py
DRConverter/Lib/converters/options.py
DRConverter/Lib/converters/otf_to_ttf.py
DRConverter/Lib/converters/sfnt_to_web.py
DRConverter/Lib/converters/ttc_to_sfnt.py
DRConverter/Lib/converters/ttf_to_otf.py
DRConverter/Lib/converters/variable_to_static.py
DRConverter/Lib/converters/web_to_sfnt.py
DRConverter/Lib/font/Font.py
DRConverter/Lib/font/VFont.py
DRConverter/Lib/font/__init__.py
DRConverter/Lib/font/tables/__init__.py
DRConverter/Lib/font/tables/name.py
DRConverter/Lib/gui/MainWindow.py
DRConverter/Lib/gui/__init__.py
DRConverter/Lib/gui/dialogs/__init__.py
DRConverter/Lib/gui/dialogs/otf2ttf_options_dialog.py
DRConverter/Lib/gui/dialogs/output_dialog.py
DRConverter/Lib/gui/dialogs/sfnt2web_options_dialog.py
DRConverter/Lib/gui/dialogs/ttc2sfnt_options_dialog.py
DRConverter/Lib/gui/dialogs/ttf2otf_options_dialog.py
DRConverter/Lib/gui/dialogs/vf2i_options_dialog.py
DRConverter/Lib/gui/dialogs/web2sfnt_options_dialog.py
DRConverter/Lib/utils/__init__.py
DRConverter/Lib/utils/subsetter.py
DRConverter/icons/icon.icns
DRConverter/icons/icon.ico
dr_converter.egg-info/PKG-INFO
dr_converter.egg-info/SOURCES.txt
dr_converter.egg-info/dependency_links.txt
dr_converter.egg-info/entry_points.txt
dr_converter.egg-info/not-zip-safe
dr_converter.egg-info/requires.txt
dr_converter.egg-info/top_level.txt